{"version":2,"kind":"Notebook","sha256":"a54405e90d0818e9c920d4ca25029da1a3315ba8d2bf29874d770bbf937e6fca","slug":"spy-keypad","location":"/notebooks/wavelet-introduction/spy-keypad.ipynb","dependencies":[],"frontmatter":{"title":"Spy Keypad","content_includes_title":true,"kernelspec":{"name":"python3","display_name":"Python 3 (ipykernel)","language":"python"},"authors":[{"nameParsed":{"literal":"Project Pythia Community","given":"Project Pythia","family":"Community"},"name":"Project Pythia Community","url":"https://projectpythia.org/","id":"contributors-myst-generated-uid-0"}],"open_access":true,"license":{"content":{"id":"Apache-2.0","url":"https://opensource.org/licenses/Apache-2.0","name":"Apache License 2.0","free":true,"osi":true},"code":{"id":"CC-BY-4.0","url":"https://creativecommons.org/licenses/by/4.0/","name":"Creative Commons Attribution 4.0 International","free":true,"CC":true}},"github":"https://github.com/projectpythia/wavelet-cookbook","copyright":"2024","numbering":{"title":{"offset":1}},"edit_url":"https://github.com/projectpythia/wavelet-cookbook/blob/main/notebooks/wavelet-introduction/spy-keypad.ipynb","thumbnail":"/wavelet-cookbook/build/18197080f5c479feecbeff82aa997d81.gif","exports":[{"format":"ipynb","filename":"spy-keypad.ipynb","url":"/wavelet-cookbook/build/spy-keypad-78ad15c537872e1935f0a9720fb42203.ipynb"}]},"widgets":{},"mdast":{"type":"root","children":[{"type":"block","kind":"notebook-content","children":[{"type":"paragraph","children":[{"type":"image","url":"/wavelet-cookbook/build/18197080f5c479feecbeff82aa997d81.gif","alt":"Typing gif from Wikipedia","key":"F7GuYxS5n8","urlSource":"https://upload.wikimedia.org/wikipedia/commons/6/6f/Programming123najra.gif"}],"key":"fWsOCXOUc1"}],"key":"kvYCm7U8Sn"},{"type":"block","kind":"notebook-content","children":[{"type":"heading","depth":1,"position":{"start":{"line":1,"column":1},"end":{"line":1,"column":1}},"children":[{"type":"text","value":"Spy Keypad","position":{"start":{"line":1,"column":1},"end":{"line":1,"column":1}},"key":"RTtarIjAse"}],"identifier":"spy-keypad","label":"Spy Keypad","html_id":"spy-keypad","implicit":true,"key":"zu1FS2JISw"},{"type":"paragraph","position":{"start":{"line":3,"column":1},"end":{"line":3,"column":1}},"children":[{"type":"strong","position":{"start":{"line":3,"column":1},"end":{"line":3,"column":1}},"children":[{"type":"text","value":"Part 2 for working with audio signals","position":{"start":{"line":3,"column":1},"end":{"line":3,"column":1}},"key":"yjK6T18xeN"}],"key":"wCi6PzEI9N"}],"key":"ooqIoZbgM7"}],"key":"zlaFIEWzfF"},{"type":"block","kind":"notebook-content","children":[{"type":"thematicBreak","position":{"start":{"line":1,"column":1},"end":{"line":1,"column":1}},"key":"anzf8OQmMO"}],"key":"SjjwXbZ7Dz"},{"type":"block","kind":"notebook-content","children":[{"type":"heading","depth":2,"position":{"start":{"line":1,"column":1},"end":{"line":1,"column":1}},"children":[{"type":"text","value":"Overview","position":{"start":{"line":1,"column":1},"end":{"line":1,"column":1}},"key":"AFzhvX03Jc"}],"identifier":"overview","label":"Overview","html_id":"overview","implicit":true,"key":"m1hXQnqJ6O"},{"type":"paragraph","position":{"start":{"line":3,"column":1},"end":{"line":3,"column":1}},"children":[{"type":"strong","position":{"start":{"line":3,"column":1},"end":{"line":3,"column":1}},"children":[{"type":"text","value":"A door is encoded with a number pad (0-9). We can’t see the door, but through nefarious means we have a recording of someone opening it. Quick! We need to decode this ","position":{"start":{"line":3,"column":1},"end":{"line":3,"column":1}},"key":"eqsde9YPHy"},{"type":"link","url":"https://github.com/ProjectPythia/wavelet-cookbook/blob/main/notebooks/data/mystery_signal.wav","position":{"start":{"line":3,"column":1},"end":{"line":3,"column":1}},"children":[{"type":"text","value":"mystery signal","position":{"start":{"line":3,"column":1},"end":{"line":3,"column":1}},"key":"Mw7FsGYsrx"}],"urlSource":"https://github.com/ProjectPythia/wavelet-cookbook/blob/main/notebooks/data/mystery_signal.wav","data":{"kind":"file","org":"ProjectPythia","repo":"wavelet-cookbook","reference":"main","file":"notebooks/data/mystery_signal.wav","raw":"https://raw.githubusercontent.com/ProjectPythia/wavelet-cookbook/main/notebooks/data/mystery_signal.wav"},"internal":false,"protocol":"github","key":"g8iCmZ7sEs"},{"type":"text","value":" and the order they appear to open the door!","position":{"start":{"line":3,"column":1},"end":{"line":3,"column":1}},"key":"SqyEnfHXoA"}],"key":"BXEeTLbj7S"}],"key":"jyKup6Fx57"},{"type":"paragraph","position":{"start":{"line":5,"column":1},"end":{"line":5,"column":1}},"children":[{"type":"text","value":"We know that the door code is set up as:","position":{"start":{"line":5,"column":1},"end":{"line":5,"column":1}},"key":"QanlQd5iQR"}],"key":"febsUGBz0k"},{"type":"list","ordered":false,"spread":false,"position":{"start":{"line":6,"column":1},"end":{"line":11,"column":1}},"children":[{"type":"listItem","spread":true,"position":{"start":{"line":6,"column":1},"end":{"line":6,"column":1}},"children":[{"type":"text","value":"A note: 0","position":{"start":{"line":6,"column":1},"end":{"line":6,"column":1}},"key":"UMhtGKh4V5"}],"key":"n9rrYVhMGZ"},{"type":"listItem","spread":true,"position":{"start":{"line":7,"column":1},"end":{"line":7,"column":1}},"children":[{"type":"text","value":"B note: 1","position":{"start":{"line":7,"column":1},"end":{"line":7,"column":1}},"key":"kzdLJnmvgs"}],"key":"UIAydwbBhH"},{"type":"listItem","spread":true,"position":{"start":{"line":8,"column":1},"end":{"line":8,"column":1}},"children":[{"type":"text","value":"C note: 2","position":{"start":{"line":8,"column":1},"end":{"line":8,"column":1}},"key":"J9IC1qlOqH"}],"key":"SdT1qS62z6"},{"type":"listItem","spread":true,"position":{"start":{"line":9,"column":1},"end":{"line":9,"column":1}},"children":[{"type":"text","value":"D note: 3","position":{"start":{"line":9,"column":1},"end":{"line":9,"column":1}},"key":"EKFmIMYaGg"}],"key":"dnEIk7wJxT"},{"type":"listItem","spread":true,"position":{"start":{"line":10,"column":1},"end":{"line":10,"column":1}},"children":[{"type":"text","value":"E note: 4","position":{"start":{"line":10,"column":1},"end":{"line":10,"column":1}},"key":"djFuTuVSAD"}],"key":"dqLxO5pood"},{"type":"listItem","spread":true,"position":{"start":{"line":11,"column":1},"end":{"line":11,"column":1}},"children":[{"type":"text","value":"F note: 5","position":{"start":{"line":11,"column":1},"end":{"line":11,"column":1}},"key":"ruF0YNn9K5"}],"key":"XojEKVVIgc"}],"key":"i7FV5gsvpm"}],"key":"WIQxkuNhiK"},{"type":"block","kind":"notebook-content","children":[{"type":"heading","depth":2,"position":{"start":{"line":1,"column":1},"end":{"line":1,"column":1}},"children":[{"type":"text","value":"Prerequisites","position":{"start":{"line":1,"column":1},"end":{"line":1,"column":1}},"key":"PEgQ64nyur"}],"identifier":"prerequisites","label":"Prerequisites","html_id":"prerequisites","implicit":true,"key":"YPYLsf41Ob"},{"type":"table","position":{"start":{"line":2,"column":1},"end":{"line":7,"column":1}},"children":[{"type":"tableRow","position":{"start":{"line":2,"column":1},"end":{"line":2,"column":1}},"children":[{"type":"tableCell","header":true,"position":{"start":{"line":2,"column":1},"end":{"line":2,"column":1}},"children":[{"type":"text","value":"Concepts","position":{"start":{"line":2,"column":1},"end":{"line":2,"column":1}},"key":"p7o2TGKmHt"}],"key":"hFPi7Kr3f2"},{"type":"tableCell","header":true,"position":{"start":{"line":2,"column":1},"end":{"line":2,"column":1}},"children":[{"type":"text","value":"Importance","position":{"start":{"line":2,"column":1},"end":{"line":2,"column":1}},"key":"cCi8qQKBPp"}],"key":"O46xPePMW4"},{"type":"tableCell","header":true,"position":{"start":{"line":2,"column":1},"end":{"line":2,"column":1}},"children":[{"type":"text","value":"Notes","position":{"start":{"line":2,"column":1},"end":{"line":2,"column":1}},"key":"nKD30Sv8ca"}],"key":"u47tCc1ft7"}],"key":"lE60CwpmOp"},{"type":"tableRow","position":{"start":{"line":4,"column":1},"end":{"line":4,"column":1}},"children":[{"type":"tableCell","position":{"start":{"line":4,"column":1},"end":{"line":4,"column":1}},"children":[{"type":"link","url":"https://foundations.projectpythia.org/core/matplotlib/matplotlib-basics.html","position":{"start":{"line":4,"column":1},"end":{"line":4,"column":1}},"children":[{"type":"text","value":"Intro to Matplotlib","position":{"start":{"line":4,"column":1},"end":{"line":4,"column":1}},"key":"QG4jnCaNI0"}],"urlSource":"https://foundations.projectpythia.org/core/matplotlib/matplotlib-basics.html","key":"vCTAGTzAmD"}],"key":"FxZNjpo9dj"},{"type":"tableCell","position":{"start":{"line":4,"column":1},"end":{"line":4,"column":1}},"children":[{"type":"text","value":"Necessary","position":{"start":{"line":4,"column":1},"end":{"line":4,"column":1}},"key":"s3Gec8CZuF"}],"key":"IivAGfnGhW"},{"type":"tableCell","position":{"start":{"line":4,"column":1},"end":{"line":4,"column":1}},"children":[{"type":"text","value":"Used to plot data","position":{"start":{"line":4,"column":1},"end":{"line":4,"column":1}},"key":"cwskZPnG9q"}],"key":"JEHVNzk4PI"}],"key":"ckRyJigKg7"},{"type":"tableRow","position":{"start":{"line":5,"column":1},"end":{"line":5,"column":1}},"children":[{"type":"tableCell","position":{"start":{"line":5,"column":1},"end":{"line":5,"column":1}},"children":[{"type":"link","url":"https://foundations.projectpythia.org/core/pandas/pandas.html","position":{"start":{"line":5,"column":1},"end":{"line":5,"column":1}},"children":[{"type":"text","value":"Intro to Pandas","position":{"start":{"line":5,"column":1},"end":{"line":5,"column":1}},"key":"qnvcpY2Hah"}],"urlSource":"https://foundations.projectpythia.org/core/pandas/pandas.html","key":"hItSHqB0Im"}],"key":"VtDkk2k1fv"},{"type":"tableCell","position":{"start":{"line":5,"column":1},"end":{"line":5,"column":1}},"children":[{"type":"text","value":"Necessary","position":{"start":{"line":5,"column":1},"end":{"line":5,"column":1}},"key":"Oxx5tMcF5X"}],"key":"ZjqQIXYSov"},{"type":"tableCell","position":{"start":{"line":5,"column":1},"end":{"line":5,"column":1}},"children":[{"type":"text","value":"Used to read in and organize data (in particular dataframes)","position":{"start":{"line":5,"column":1},"end":{"line":5,"column":1}},"key":"JQ4WavVWKN"}],"key":"Zbjp8MYrVt"}],"key":"QUkyZFx89i"},{"type":"tableRow","position":{"start":{"line":6,"column":1},"end":{"line":6,"column":1}},"children":[{"type":"tableCell","position":{"start":{"line":6,"column":1},"end":{"line":6,"column":1}},"children":[{"type":"link","url":"https://foundations.projectpythia.org/core/numpy/numpy-basics.html","position":{"start":{"line":6,"column":1},"end":{"line":6,"column":1}},"children":[{"type":"text","value":"Intro to Numpy","position":{"start":{"line":6,"column":1},"end":{"line":6,"column":1}},"key":"RZcGGOBUmN"}],"urlSource":"https://foundations.projectpythia.org/core/numpy/numpy-basics.html","key":"X9xeRnpCpQ"}],"key":"IOWnb4xbZH"},{"type":"tableCell","position":{"start":{"line":6,"column":1},"end":{"line":6,"column":1}},"children":[{"type":"text","value":"Necessary","position":{"start":{"line":6,"column":1},"end":{"line":6,"column":1}},"key":"g0auviiRPA"}],"key":"AknWz21Qht"},{"type":"tableCell","position":{"start":{"line":6,"column":1},"end":{"line":6,"column":1}},"children":[{"type":"text","value":"Used to work with large arrays","position":{"start":{"line":6,"column":1},"end":{"line":6,"column":1}},"key":"bRucW7n4bd"}],"key":"EBmzNbhi3T"}],"key":"VHYYSVL8vv"},{"type":"tableRow","position":{"start":{"line":7,"column":1},"end":{"line":7,"column":1}},"children":[{"type":"tableCell","position":{"start":{"line":7,"column":1},"end":{"line":7,"column":1}},"children":[{"type":"link","url":"https://docs.scipy.org/doc/scipy-1.13.1/tutorial/fft.html","position":{"start":{"line":7,"column":1},"end":{"line":7,"column":1}},"children":[{"type":"text","value":"Intro to SciPy","position":{"start":{"line":7,"column":1},"end":{"line":7,"column":1}},"key":"XkmwhvIItx"}],"urlSource":"https://docs.scipy.org/doc/scipy-1.13.1/tutorial/fft.html","key":"FisDAqYKE6"}],"key":"wsCrcSFY3T"},{"type":"tableCell","position":{"start":{"line":7,"column":1},"end":{"line":7,"column":1}},"children":[{"type":"text","value":"Helpful","position":{"start":{"line":7,"column":1},"end":{"line":7,"column":1}},"key":"kUiz1mCuFV"}],"key":"F0YWivDHi9"},{"type":"tableCell","position":{"start":{"line":7,"column":1},"end":{"line":7,"column":1}},"children":[{"type":"text","value":"Used to work with .wav files and built-in Fast Fourier Transform","position":{"start":{"line":7,"column":1},"end":{"line":7,"column":1}},"key":"FICIbIGbA0"}],"key":"WkRwBd7mHp"}],"key":"ChYtZfVi5e"}],"key":"RcWfp3KWI4"},{"type":"list","ordered":false,"spread":false,"position":{"start":{"line":9,"column":1},"end":{"line":9,"column":1}},"children":[{"type":"listItem","spread":true,"position":{"start":{"line":9,"column":1},"end":{"line":9,"column":1}},"children":[{"type":"strong","position":{"start":{"line":9,"column":1},"end":{"line":9,"column":1}},"children":[{"type":"text","value":"Time to learn","position":{"start":{"line":9,"column":1},"end":{"line":9,"column":1}},"key":"JjiuSKNu6J"}],"key":"XFWdoCkr2D"},{"type":"text","value":": 30 minutes","position":{"start":{"line":9,"column":1},"end":{"line":9,"column":1}},"key":"EFQJNLh7Ei"}],"key":"gUNRTEdpvC"}],"key":"juCtvQzizH"}],"key":"X0RGdGI4JO"},{"type":"block","kind":"notebook-content","children":[{"type":"thematicBreak","position":{"start":{"line":1,"column":1},"end":{"line":1,"column":1}},"key":"TCTcrc8AqD"}],"key":"rRsR6wwKwO"},{"type":"block","kind":"notebook-content","children":[{"type":"heading","depth":2,"position":{"start":{"line":1,"column":1},"end":{"line":1,"column":1}},"children":[{"type":"text","value":"Imports","position":{"start":{"line":1,"column":1},"end":{"line":1,"column":1}},"key":"QTgcM1Naij"}],"identifier":"imports","label":"Imports","html_id":"imports","implicit":true,"key":"B3qGH6qSh9"}],"key":"NDLWGJvp1X"},{"type":"block","kind":"notebook-code","children":[{"type":"code","lang":"python","executable":true,"value":"import numpy as np                          # working with arrays\nimport pandas as pd                         # working with dataframes\nfrom scipy.io import wavfile                # loading in wav files\nimport matplotlib.pyplot as plt             # plot data\nfrom scipy.fftpack import fft, fftfreq      # working with Fourier Transforms\n\nimport pywt                                 # PyWavelets","key":"RCJuhnWsYm"},{"type":"output","id":"AWYtJVHRTgdKaRu5b2SLp","data":[],"key":"V0itOslUjq"}],"key":"afEU1bMAJg"},{"type":"block","kind":"notebook-content","children":[{"type":"heading","depth":2,"position":{"start":{"line":1,"column":1},"end":{"line":1,"column":1}},"children":[{"type":"text","value":"Extract audio .wav file","position":{"start":{"line":1,"column":1},"end":{"line":1,"column":1}},"key":"UpXaZ7otRL"}],"identifier":"extract-audio-wav-file","label":"Extract audio .wav file","html_id":"extract-audio-wav-file","implicit":true,"key":"JKd6Yc1Aoq"},{"type":"paragraph","position":{"start":{"line":2,"column":1},"end":{"line":2,"column":1}},"children":[{"type":"text","value":"As when working with the “Jingle Bells” song file, any .wav input file contains information about the amplitude at every point in the file. The frequency of the note will determine which chord each part of the piece represents.","position":{"start":{"line":2,"column":1},"end":{"line":2,"column":1}},"key":"UAjM4hGc16"}],"key":"SY8UtZYa8w"}],"key":"oZhAoRRD78"},{"type":"block","kind":"notebook-code","children":[{"type":"code","lang":"python","executable":true,"value":"sampleRate, signalData = wavfile.read('../data/mystery_signal.wav')\n\nduration = len(signalData) / sampleRate\ntime = np.arange(0, duration, 1/sampleRate) \n\nprint(f\"Sample Rate: {sampleRate}\")\nprint(f\"duration = {duration} seconds\")\nprint(f\"Total length in time steps = {len(time)}\")","key":"kJk5gfvoVR"},{"type":"output","id":"uBeZwvbn-RLq9_uXR7hQZ","data":[{"output_type":"stream","name":"stdout","text":"Sample Rate: 10000\nduration = 6.0 seconds\nTotal length in time steps = 60000\n"}],"key":"pNVmuXbHgr"}],"key":"fbvIBBflqm"},{"type":"block","kind":"notebook-content","children":[{"type":"heading","depth":2,"position":{"start":{"line":1,"column":1},"end":{"line":1,"column":1}},"children":[{"type":"text","value":"Let’s Give the Data a Look!","position":{"start":{"line":1,"column":1},"end":{"line":1,"column":1}},"key":"g0tcCFsl1V"}],"identifier":"lets-give-the-data-a-look","label":"Let’s Give the Data a Look!","html_id":"lets-give-the-data-a-look","implicit":true,"key":"qkHZ9br3NC"},{"type":"paragraph","position":{"start":{"line":3,"column":1},"end":{"line":3,"column":1}},"children":[{"type":"text","value":"It is always good practice to view the data that we have collected. First, let’s organize the data into a ","position":{"start":{"line":3,"column":1},"end":{"line":3,"column":1}},"key":"BURxv6FoFW"},{"type":"inlineCode","value":"pandas","position":{"start":{"line":3,"column":1},"end":{"line":3,"column":1}},"key":"Tt7PAtTzx0"},{"type":"text","value":" dataframe to organize the amplitude and time stamps.","position":{"start":{"line":3,"column":1},"end":{"line":3,"column":1}},"key":"zzw4DKPqIa"}],"key":"Bw8OrGL8F6"}],"key":"AsgYvDH5OC"},{"type":"block","kind":"notebook-code","children":[{"type":"code","lang":"python","executable":true,"value":"signal_df = pd.DataFrame({'time (seconds)': time, 'amplitude': signalData})\nsignal_df.head()","key":"FTsf98Q6yG"},{"type":"output","id":"Gvosy7qUw-lsIZsWteK7m","data":[{"output_type":"execute_result","execution_count":3,"metadata":{},"data":{"text/plain":{"content":"   time (seconds)  amplitude\n0          0.0000      11182\n1          0.0001      29148\n2          0.0002       2847\n3          0.0003      14564\n4          0.0004      21618","content_type":"text/plain"},"text/html":{"content":"<div>\n<style scoped>\n    .dataframe tbody tr th:only-of-type {\n        vertical-align: middle;\n    }\n\n    .dataframe tbody tr th {\n        vertical-align: top;\n    }\n\n    .dataframe thead th {\n        text-align: right;\n    }\n</style>\n<table border=\"1\" class=\"dataframe\">\n  <thead>\n    <tr style=\"text-align: right;\">\n      <th></th>\n      <th>time (seconds)</th>\n      <th>amplitude</th>\n    </tr>\n  </thead>\n  <tbody>\n    <tr>\n      <th>0</th>\n      <td>0.0000</td>\n      <td>11182</td>\n    </tr>\n    <tr>\n      <th>1</th>\n      <td>0.0001</td>\n      <td>29148</td>\n    </tr>\n    <tr>\n      <th>2</th>\n      <td>0.0002</td>\n      <td>2847</td>\n    </tr>\n    <tr>\n      <th>3</th>\n      <td>0.0003</td>\n      <td>14564</td>\n    </tr>\n    <tr>\n      <th>4</th>\n      <td>0.0004</td>\n      <td>21618</td>\n    </tr>\n  </tbody>\n</table>\n</div>","content_type":"text/html"}}}],"key":"IMASCp2Vc5"}],"key":"qsjofMWUaT"},{"type":"block","kind":"notebook-content","children":[{"type":"heading","depth":3,"position":{"start":{"line":1,"column":1},"end":{"line":1,"column":1}},"children":[{"type":"text","value":"Plot a Small Sample of the .wav File","position":{"start":{"line":1,"column":1},"end":{"line":1,"column":1}},"key":"PyD8UMcsgU"}],"identifier":"plot-a-small-sample-of-the-wav-file","label":"Plot a Small Sample of the .wav File","html_id":"plot-a-small-sample-of-the-wav-file","implicit":true,"key":"TK7XYhIFmh"},{"type":"paragraph","position":{"start":{"line":3,"column":1},"end":{"line":3,"column":1}},"children":[{"type":"text","value":"Plot a small subsample of the .wav to visualize the input data.","position":{"start":{"line":3,"column":1},"end":{"line":3,"column":1}},"key":"pUyVgS8Osg"}],"key":"YQpqPHxdyy"}],"key":"Fh15MC1T9Q"},{"type":"block","kind":"notebook-code","children":[{"type":"code","lang":"python","executable":true,"value":"fig, ax = plt.subplots(figsize=(8, 8))\nfig = plt.plot(signal_df[\"time (seconds)\"], signal_df[\"amplitude\"])\nplt.title(\"Subsample of Mystery Audio File\")\nax.set_xlim(signal_df[\"time (seconds)\"][2000], signal_df[\"time (seconds)\"][4000])\nplt.xlabel(\"Time (seconds)\")\nplt.ylabel(\"Amplitude\")\nplt.show()","key":"rMYWwfmUbN"},{"type":"output","id":"sZfPY_Uffnttoaf3ewF7F","data":[{"output_type":"display_data","metadata":{},"data":{"text/plain":{"content":"<Figure size 800x800 with 1 Axes>","content_type":"text/plain"},"image/png":{"content_type":"image/png","hash":"961b29bdc967936c92448000d804c88b","path":"/wavelet-cookbook/build/961b29bdc967936c92448000d804c88b.png"}}}],"key":"DUNds7JXjx"}],"key":"vc0OxzB10y"},{"type":"block","kind":"notebook-content","children":[{"type":"heading","depth":2,"position":{"start":{"line":1,"column":1},"end":{"line":1,"column":1}},"children":[{"type":"text","value":"Wavelet Analysis: Power Spectrum","position":{"start":{"line":1,"column":1},"end":{"line":1,"column":1}},"key":"NHAVd0LWG7"}],"identifier":"wavelet-analysis-power-spectrum","label":"Wavelet Analysis: Power Spectrum","html_id":"wavelet-analysis-power-spectrum","implicit":true,"key":"yqUAq4pJn6"},{"type":"paragraph","position":{"start":{"line":3,"column":1},"end":{"line":3,"column":1}},"children":[{"type":"text","value":"The power spectrum plots the real component of the complex number returns from wavelet coefficients. This will return information about the frequency and time that we need to use to determine which notes are used in what order for the keypad.","position":{"start":{"line":3,"column":1},"end":{"line":3,"column":1}},"key":"kG1UCUJlUr"}],"key":"wA7ERKG18r"},{"type":"paragraph","position":{"start":{"line":5,"column":1},"end":{"line":5,"column":1}},"children":[{"type":"text","value":"For the purpose of this example, we will use the Morlet mother wavelet. Morlet is one type of mother wavelet useful for working with audio signals and is a good general wavelet to start with when analyzing frequencies of a signal.","position":{"start":{"line":5,"column":1},"end":{"line":5,"column":1}},"key":"bI45vv6Cya"}],"key":"KCgQgGkJdC"},{"type":"paragraph","position":{"start":{"line":7,"column":1},"end":{"line":7,"column":1}},"children":[{"type":"text","value":"However, choosing which wavelet to use is an important step as different wavelets will be sensitive to different features in time-series data.","position":{"start":{"line":7,"column":1},"end":{"line":7,"column":1}},"key":"E12XuCRxh1"}],"key":"xpU7ZbpK5P"},{"type":"paragraph","position":{"start":{"line":9,"column":1},"end":{"line":9,"column":1}},"children":[{"type":"link","url":"https://www.mathworks.com/help/wavelet/gs/choose-a-wavelet.html","position":{"start":{"line":9,"column":1},"end":{"line":9,"column":1}},"children":[{"type":"text","value":"To learn more!","position":{"start":{"line":9,"column":1},"end":{"line":9,"column":1}},"key":"Jt1knZBxP5"}],"urlSource":"https://www.mathworks.com/help/wavelet/gs/choose-a-wavelet.html","key":"eHqvpeSb5z"}],"key":"WCHnQnkU1T"}],"key":"PwXYI49wlT"},{"type":"block","kind":"notebook-code","children":[{"type":"code","lang":"python","executable":true,"value":"wavelet_mother = \"morl\" # morlet mother wavelet\n\n# scale determines how squished or stretched a wavelet is\nscales = np.arange(1, 40)\nwavelet_coeffs, freqs = pywt.cwt(signalData, scales, wavelet = wavelet_mother)\n\n# Shape of wavelet transform\nprint(f\"size {wavelet_coeffs.shape} with {wavelet_coeffs.shape[0]} scales and {wavelet_coeffs.shape[1]} time steps\")\nprint(f\"x-axis is: {wavelet_coeffs.shape[1]}\")\nprint(f\"y-axis is: {wavelet_coeffs.shape[0]}\")","key":"i1TkSjVHUR"},{"type":"output","id":"2WKUqBdxiJnaWgLZEq2cp","data":[{"output_type":"stream","name":"stdout","text":"size (39, 60000) with 39 scales and 60000 time steps\nx-axis is: 60000\ny-axis is: 39\n"}],"key":"MdZoKZDzCI"}],"key":"CAO2HKNcGX"},{"type":"block","kind":"notebook-content","children":[{"type":"heading","depth":4,"position":{"start":{"line":1,"column":1},"end":{"line":1,"column":1}},"children":[{"type":"text","value":"Plot Scalogram","position":{"start":{"line":1,"column":1},"end":{"line":1,"column":1}},"key":"zhJOzmsUYu"}],"identifier":"plot-scalogram","label":"Plot Scalogram","html_id":"plot-scalogram","implicit":true,"key":"NnOdrQS40n"},{"type":"paragraph","position":{"start":{"line":3,"column":1},"end":{"line":3,"column":1}},"children":[{"type":"text","value":"We will be plotting the wavelet as a scalogram, where the presence of a strong match to a specific frequency will be a darker color. This will create distinct bands of a dark color where a specific frequency is present.","position":{"start":{"line":3,"column":1},"end":{"line":3,"column":1}},"key":"oO4JI3wLJz"}],"key":"vCI0UgHGG0"}],"key":"hLWTjH6ZB1"},{"type":"block","kind":"notebook-code","children":[{"type":"code","lang":"python","executable":true,"value":"fig, ax = plt.subplots(figsize=(8, 8))\ndata = np.log2(np.square(abs(wavelet_coeffs))) # compare the magntiude\nplt.xlabel(\"Time Steps\")\nplt.ylabel(\"Scale Sensitivity\")\nplt.imshow(data, \n           vmax=(data).max(), vmin=(data).min(),\n           cmap=\"coolwarm\", aspect=\"auto\")\nplt.colorbar()\nplt.show()","key":"t3vZGgwSAo"},{"type":"output","id":"pjMEdu81NRAs02yYhVjV3","data":[{"output_type":"display_data","metadata":{},"data":{"text/plain":{"content":"<Figure size 800x800 with 2 Axes>","content_type":"text/plain"},"image/png":{"content_type":"image/png","hash":"a0dae0db3c496fc8dad53db1f71b128c","path":"/wavelet-cookbook/build/a0dae0db3c496fc8dad53db1f71b128c.png"}}}],"key":"LDltgp7azg"}],"key":"cH0utujCyl"},{"type":"block","kind":"notebook-content","children":[{"type":"heading","depth":2,"position":{"start":{"line":1,"column":1},"end":{"line":1,"column":1}},"children":[{"type":"text","value":"Behold! Distinct Bands of Frequencies!","position":{"start":{"line":1,"column":1},"end":{"line":1,"column":1}},"key":"MGl9U8GIAi"}],"identifier":"behold-distinct-bands-of-frequencies","label":"Behold! Distinct Bands of Frequencies!","html_id":"behold-distinct-bands-of-frequencies","implicit":true,"key":"AreLhcuTs1"},{"type":"paragraph","position":{"start":{"line":2,"column":1},"end":{"line":2,"column":1}},"children":[{"type":"text","value":"Each distinct band represents a note. So, we can see that the data at the beginning and at the end is random noise, with no distinct frequency. But at 1 second, a distinct note that lasts for 1 second, followed by three additional distinct bands. We now know the code is four numbers long. But now we need to determine what the numbers are and what their order is. Let’s see where the possible note frequencies we have by overlaying the frequencies of each note onto the wavelet scalogram.","position":{"start":{"line":2,"column":1},"end":{"line":2,"column":1}},"key":"rteXwruvTM"}],"key":"jL3LmPNudJ"},{"type":"div","class":"admonition alert alert-info","children":[{"type":"paragraph","children":[{"type":"text","value":"Important Note","key":"f7fW7I01rW"}],"key":"INk8ngeyEV"},{"type":"text","value":"To convert Hz frequency to a ","key":"yc0fsUPANC"},{"type":"inlineCode","value":"scale = hz *.0001","key":"fRmvBuJqKd"},{"type":"text","value":" (where 0.01 is 100 Hz sampling) then apply ","key":"imx5208OTT"},{"type":"inlineCode","value":"frequency2scale","key":"XSsKt3guMl"},{"type":"text","value":" PyWavelets function","key":"g8i71oEY1H"}],"key":"Np1nIntdU7"}],"key":"u2aed4LTco"},{"type":"block","kind":"notebook-code","children":[{"type":"code","lang":"python","executable":true,"value":"fig, ax = plt.subplots(figsize=(8, 8))\n\n# Overlay frequency of notes as dotted lines\nsample_rate = 1/sampleRate\na_freq = pywt.frequency2scale(wavelet_mother, 440*sample_rate)\nplt.axhline(y=a_freq, color='lightpink', linestyle='--', label='A') # A note: 440 hz\nb_freq = pywt.frequency2scale(wavelet_mother, 494*sample_rate)\nplt.axhline(y=b_freq, color=\"blue\", linestyle='--', label='B')      # B Note: 494 hz\nc_freq = pywt.frequency2scale(wavelet_mother, 261*sample_rate)\nplt.axhline(y=c_freq, color='lightblue', linestyle='--', label='C') # C Note: 261 hz\nd_freq = pywt.frequency2scale(wavelet_mother, 293*sample_rate)\nplt.axhline(y=d_freq, color='green', linestyle='--', label='D')     # D Note: 293 hz\ne_freq = pywt.frequency2scale(wavelet_mother, 330*sample_rate)\nplt.axhline(y=e_freq, color='orange', linestyle='--', label='E')    # E Note: 330 hz\nf_freq = pywt.frequency2scale(wavelet_mother, 350*sample_rate)\nplt.axhline(y=f_freq, color='grey', linestyle='--', label='F')      # F Note: 350 hz\ng_freq = pywt.frequency2scale(wavelet_mother, 392*sample_rate)\nplt.axhline(y=g_freq, color='purple', linestyle='--', label='G')    # G Note: 392 hz\n\n# Plot Power scalogram\npower = np.log2(np.square(abs(wavelet_coeffs))) # compare the magntiude\nplt.title(\"Note Frequency as Scale\")\nplt.xlabel(\"Time Steps\")\nplt.ylabel(\"Scale Sensitivity\")\nplt.imshow(power, \n           vmax=(power).max(), vmin=(power).min(),\n           cmap=\"coolwarm\", aspect=\"auto\")\nplt.legend()\nplt.show()","key":"BoItvOzxl0"},{"type":"output","id":"bdOnFxRIvuxywspF59Bv7","data":[{"output_type":"display_data","metadata":{},"data":{"text/plain":{"content":"<Figure size 800x800 with 1 Axes>","content_type":"text/plain"},"image/png":{"content_type":"image/png","hash":"6f721f5ec22da0fd94a30a4da97925b3","path":"/wavelet-cookbook/build/6f721f5ec22da0fd94a30a4da97925b3.png"}}}],"key":"tyYbU6fv5X"}],"key":"pzfhPW1aN5"},{"type":"block","kind":"notebook-content","children":[{"type":"heading","depth":2,"position":{"start":{"line":1,"column":1},"end":{"line":1,"column":1}},"children":[{"type":"text","value":"But Which Match Best?","position":{"start":{"line":1,"column":1},"end":{"line":1,"column":1}},"key":"iJVUmmfn6b"}],"identifier":"but-which-match-best","label":"But Which Match Best?","html_id":"but-which-match-best","implicit":true,"key":"WhKABVwUYr"},{"type":"paragraph","position":{"start":{"line":3,"column":1},"end":{"line":3,"column":1}},"children":[{"type":"text","value":"We are looking for a note frequency that best lines up with the darkest part of each band. The first and the last band seem like the same note, but is it closer to an A note or a B note?","position":{"start":{"line":3,"column":1},"end":{"line":3,"column":1}},"key":"ldg6U0TKKC"}],"key":"JrfU05j5jY"},{"type":"paragraph","position":{"start":{"line":5,"column":1},"end":{"line":5,"column":1}},"children":[{"type":"text","value":"Let’s see if we can use Fourier Transform to get a smaller range of notes to chose from.","position":{"start":{"line":5,"column":1},"end":{"line":5,"column":1}},"key":"PWOHrP2CCe"}],"key":"NJvdYKeiR3"}],"key":"WL89ipunlA"},{"type":"block","kind":"notebook-content","children":[{"type":"heading","depth":2,"position":{"start":{"line":1,"column":1},"end":{"line":1,"column":1}},"children":[{"type":"text","value":"Fast Fourier Transform","position":{"start":{"line":1,"column":1},"end":{"line":1,"column":1}},"key":"dVG7IBSVYS"}],"identifier":"fast-fourier-transform","label":"Fast Fourier Transform","html_id":"fast-fourier-transform","implicit":true,"key":"AlzA2m6ump"}],"key":"uKSNtLephJ"},{"type":"block","kind":"notebook-code","children":[{"type":"code","lang":"python","executable":true,"value":"fourier_transform = abs(fft(signalData))\nfreqs = fftfreq(len(fourier_transform), sample_rate)","key":"qOsKUXbUrA"},{"type":"output","id":"R3wyaixX2WsyIGa6ONzBN","data":[],"key":"dKziDGHpuo"}],"key":"LcAJqVqU9I"},{"type":"block","kind":"notebook-code","children":[{"type":"code","lang":"python","executable":true,"value":"fig, ax = plt.subplots(figsize=(8, 8))\nplt.plot(freqs, fourier_transform)\nax.set_xlim(left=200, right=500) \nplt.axvline(x=440, color=\"lightpink\", label=\"A\",alpha=0.5) # A note: 440 hz\nplt.axvline(x=494, color=\"blue\", label=\"B\",alpha=0.5)      # B Note: 494 hz\nplt.axvline(x=261, color=\"lightblue\", label=\"C\",alpha=0.5) # C Note: 261 hz\nplt.axvline(x=293, color=\"green\", label=\"D\",alpha=0.5)     # D Note: 293 hz\nplt.axvline(x=330, color=\"orange\", label=\"E\",alpha=0.5)    # E Note: 330 hz\nplt.axvline(x=350, color=\"grey\", label=\"F\",alpha=0.5)      # F Note: 350 hz\nplt.axvline(x=392, color=\"purple\", label=\"G\",alpha=0.5)    # G Note: 392 hz\nplt.title(\"Signal Frequency Prevalence (FFT)\")\nplt.xlabel('Frequency (Hz)')\nplt.ylabel('Amplitude')\nplt.legend()\nplt.show()","key":"bzesm6uUtD"},{"type":"output","id":"L0iJPvr6CFOYhU_yRxcWi","data":[{"output_type":"display_data","metadata":{},"data":{"text/plain":{"content":"<Figure size 800x800 with 1 Axes>","content_type":"text/plain"},"image/png":{"content_type":"image/png","hash":"511f3dffa2fa2df2198acc3d942e2d59","path":"/wavelet-cookbook/build/511f3dffa2fa2df2198acc3d942e2d59.png"}}}],"key":"XJdjGKTXUb"}],"key":"po6eHkUMiq"},{"type":"block","kind":"notebook-content","children":[{"type":"heading","depth":2,"position":{"start":{"line":1,"column":1},"end":{"line":1,"column":1}},"children":[{"type":"text","value":"Perfect, There are Three Notes!","position":{"start":{"line":1,"column":1},"end":{"line":1,"column":1}},"key":"XKGxAJfUho"}],"identifier":"perfect-there-are-three-notes","label":"Perfect, There are Three Notes!","html_id":"perfect-there-are-three-notes","implicit":true,"key":"egsyVU6xmr"},{"type":"paragraph","position":{"start":{"line":3,"column":1},"end":{"line":3,"column":1}},"children":[{"type":"text","value":"Three notes stand out, and one note is used about twice as much as the other two: A, B, F.","position":{"start":{"line":3,"column":1},"end":{"line":3,"column":1}},"key":"ZAhfXrDZ3f"}],"key":"dimPhXVaGJ"}],"key":"hnlewwYap3"},{"type":"block","kind":"notebook-code","children":[{"type":"code","lang":"python","executable":true,"value":"fig, ax = plt.subplots(figsize=(8, 8))\n\n# Overlay frequency of notes as dotted lines\nsample_rate = 1/sampleRate\na_freq = pywt.frequency2scale(wavelet_mother, 440*sample_rate)\nplt.axhline(y=a_freq, color='cyan', linestyle='--', label='A')\nb_freq = pywt.frequency2scale(wavelet_mother, 494*sample_rate)\nplt.axhline(y=b_freq, color=\"green\", linestyle='--', label='B')\nf_freq = pywt.frequency2scale(wavelet_mother, 350*sample_rate)\nplt.axhline(y=f_freq, color='grey', linestyle='--', label='F')\n\n# Plot Power scalogram\npower = np.log2(np.square(abs(wavelet_coeffs))) # compare the magnitude\nplt.title(\"Note Frequency as Scale\")\nplt.xlabel(\"Time Steps\")\nplt.ylabel(\"Scale Sensitivity\")\nplt.imshow(power, \n           vmax=(power).max(), vmin=(power).min(),\n           cmap=\"coolwarm\", aspect=\"auto\")\nplt.legend()\nplt.show()","key":"KZdDa3eAHb"},{"type":"output","id":"l0fC9UbAegkeYFSBGCHCP","data":[{"output_type":"display_data","metadata":{},"data":{"text/plain":{"content":"<Figure size 800x800 with 1 Axes>","content_type":"text/plain"},"image/png":{"content_type":"image/png","hash":"645c45c3e28bc2b34327f47a3323c743","path":"/wavelet-cookbook/build/645c45c3e28bc2b34327f47a3323c743.png"}}}],"key":"jdTwdBmlXc"}],"key":"uBO9inkkWa"},{"type":"block","kind":"notebook-content","children":[{"type":"heading","depth":2,"position":{"start":{"line":1,"column":1},"end":{"line":1,"column":1}},"children":[{"type":"text","value":"Three Notes Played Over Six Seconds","position":{"start":{"line":1,"column":1},"end":{"line":1,"column":1}},"key":"kH1jlz2Yy9"}],"identifier":"three-notes-played-over-six-seconds","label":"Three Notes Played Over Six Seconds","html_id":"three-notes-played-over-six-seconds","implicit":true,"key":"IPTVxISxbG"},{"type":"paragraph","position":{"start":{"line":3,"column":1},"end":{"line":3,"column":1}},"children":[{"type":"text","value":"We have the keypad solution! The three notes are played (sometimes repeated) over the course of the six seconds.","position":{"start":{"line":3,"column":1},"end":{"line":3,"column":1}},"key":"uGlX3rbfMJ"}],"key":"WcYz87w97y"},{"type":"heading","depth":3,"position":{"start":{"line":5,"column":1},"end":{"line":5,"column":1}},"children":[{"type":"text","value":"A, B, F, A","position":{"start":{"line":5,"column":1},"end":{"line":5,"column":1}},"key":"GaOgkP9kKk"}],"identifier":"a-b-f-a","label":"A, B, F, A","html_id":"a-b-f-a","implicit":true,"key":"Fph5ByOH3n"},{"type":"paragraph","position":{"start":{"line":8,"column":1},"end":{"line":8,"column":1}},"children":[{"type":"text","value":"From our original problem, we know that the door code is set up as:","position":{"start":{"line":8,"column":1},"end":{"line":8,"column":1}},"key":"DY00TXsYlN"}],"key":"Gy45l3jYMH"},{"type":"list","ordered":false,"spread":false,"position":{"start":{"line":9,"column":1},"end":{"line":15,"column":1}},"children":[{"type":"listItem","spread":true,"position":{"start":{"line":9,"column":1},"end":{"line":9,"column":1}},"children":[{"type":"text","value":"A note: 0","position":{"start":{"line":9,"column":1},"end":{"line":9,"column":1}},"key":"yXiaKkkKeo"}],"key":"o5nR8s1CRO"},{"type":"listItem","spread":true,"position":{"start":{"line":10,"column":1},"end":{"line":10,"column":1}},"children":[{"type":"text","value":"B note: 1","position":{"start":{"line":10,"column":1},"end":{"line":10,"column":1}},"key":"w964CWMeWV"}],"key":"cRxJKAdlDb"},{"type":"listItem","spread":true,"position":{"start":{"line":11,"column":1},"end":{"line":11,"column":1}},"children":[{"type":"text","value":"C note: 2","position":{"start":{"line":11,"column":1},"end":{"line":11,"column":1}},"key":"NCN4MWr8VQ"}],"key":"IStWFhP4W7"},{"type":"listItem","spread":true,"position":{"start":{"line":12,"column":1},"end":{"line":12,"column":1}},"children":[{"type":"text","value":"D note: 3","position":{"start":{"line":12,"column":1},"end":{"line":12,"column":1}},"key":"HqMhXZNtW8"}],"key":"hEn1HMyKdY"},{"type":"listItem","spread":true,"position":{"start":{"line":13,"column":1},"end":{"line":13,"column":1}},"children":[{"type":"text","value":"E note: 4","position":{"start":{"line":13,"column":1},"end":{"line":13,"column":1}},"key":"F2RCQGoc48"}],"key":"tdXFYefdEW"},{"type":"listItem","spread":true,"position":{"start":{"line":14,"column":1},"end":{"line":15,"column":1}},"children":[{"type":"text","value":"F note: 5","position":{"start":{"line":14,"column":1},"end":{"line":14,"column":1}},"key":"ckuYtym7NS"}],"key":"HF0YmJMS2W"}],"key":"FdJDIGRBJc"},{"type":"paragraph","position":{"start":{"line":16,"column":1},"end":{"line":16,"column":1}},"children":[{"type":"text","value":"The solution to the door password is:","position":{"start":{"line":16,"column":1},"end":{"line":16,"column":1}},"key":"j1iWa5ngdc"}],"key":"Dw7rXLoxAe"},{"type":"heading","depth":3,"position":{"start":{"line":18,"column":1},"end":{"line":18,"column":1}},"children":[{"type":"text","value":"0, 1, 5, 0","position":{"start":{"line":18,"column":1},"end":{"line":18,"column":1}},"key":"zLiEGger4I"}],"identifier":"id-0-1-5-0","label":"0, 1, 5, 0","html_id":"id-0-1-5-0","implicit":true,"key":"eUfkrgaoBH"}],"key":"JCcYY4hNge"},{"type":"block","kind":"notebook-content","children":[{"type":"thematicBreak","position":{"start":{"line":1,"column":1},"end":{"line":1,"column":1}},"key":"DFvbplA3pL"}],"key":"fn7ekZPxe7"},{"type":"block","kind":"notebook-content","children":[{"type":"heading","depth":2,"position":{"start":{"line":1,"column":1},"end":{"line":1,"column":1}},"children":[{"type":"text","value":"Summary","position":{"start":{"line":1,"column":1},"end":{"line":1,"column":1}},"key":"uH3L90Rftl"}],"identifier":"summary","label":"Summary","html_id":"summary","implicit":true,"key":"XCVvkNp2to"},{"type":"paragraph","position":{"start":{"line":2,"column":1},"end":{"line":2,"column":1}},"children":[{"type":"text","value":"Now we’ve had a chance to work with unknown input values, but within an expected range. Different time-series data will have different ranges of expected frequencies, and with Fourier Transform and wavelet analysis it is possible to pull out such relevant data.","position":{"start":{"line":2,"column":1},"end":{"line":2,"column":1}},"key":"VveH8xzDxn"}],"key":"IaZb8dr6Hf"},{"type":"heading","depth":3,"position":{"start":{"line":4,"column":1},"end":{"line":4,"column":1}},"children":[{"type":"text","value":"What’s next?","position":{"start":{"line":4,"column":1},"end":{"line":4,"column":1}},"key":"udkWIWkiJf"}],"identifier":"whats-next","label":"What’s next?","html_id":"whats-next","implicit":true,"key":"BKDifFRqQf"},{"type":"paragraph","position":{"start":{"line":6,"column":1},"end":{"line":6,"column":1}},"children":[{"type":"strong","position":{"start":{"line":6,"column":1},"end":{"line":6,"column":1}},"children":[{"type":"text","value":"Up next: apply wavelets transform and work with weather data!","position":{"start":{"line":6,"column":1},"end":{"line":6,"column":1}},"key":"bFeDh2KqPf"}],"key":"FIZMZqOMDG"}],"key":"iE4hsy8Hqm"}],"key":"uODyfDVn0N"}],"key":"DuzPG2y5PS"},"references":{"cite":{"order":[],"data":{}}},"footer":{"navigation":{"prev":{"title":"PyWavelets and Jingle Bells","url":"/jingle-bells","group":"Introduction"},"next":{"title":"Atmospheric Data: Nino 3 SST Index","url":"/nino3","group":"Geoscience Workflows"}}},"domain":"http://localhost:3000"}